<?xml version="1.0" encoding="utf-8"?>
<ArrayOfTextSyntaxItem xmlns:xsi="http://www.w3.org/2001/XMLSchema-instance" xmlns:xsd="http://www.w3.org/2001/XMLSchema">
  <TextSyntaxItem>
    <SerializableName>Plain Text</SerializableName>
    <SerializableDescription>Plain Text</SerializableDescription>
    <SerializableIcon>text-x-generic</SerializableIcon>
    <Syntax>text</Syntax>
  </TextSyntaxItem>
  <TextSyntaxItem>
    <SerializableName>Actionscript</SerializableName>
    <SerializableDescription>Actionscript</SerializableDescription>
    <SerializableIcon>text-x-generic</SerializableIcon>
    <Syntax>actionscript</Syntax>
  </TextSyntaxItem>
  <TextSyntaxItem>
    <SerializableName>Ada</SerializableName>
    <SerializableDescription>Ada</SerializableDescription>
    <SerializableIcon>text-x-generic</SerializableIcon>
    <Syntax>ada</Syntax>
  </TextSyntaxItem>
  <TextSyntaxItem>
    <SerializableName>Apache Config</SerializableName>
    <SerializableDescription>Apache Config</SerializableDescription>
    <SerializableIcon>text-x-generic</SerializableIcon>
    <Syntax>apache</Syntax>
  </TextSyntaxItem>
  <TextSyntaxItem>
    <SerializableName>AppleScript</SerializableName>
    <SerializableDescription>AppleScript</SerializableDescription>
    <SerializableIcon>text-x-generic</SerializableIcon>
    <Syntax>applescript</Syntax>
  </TextSyntaxItem>
  <TextSyntaxItem>
    <SerializableName>ASP</SerializableName>
    <SerializableDescription>ASP</SerializableDescription>
    <SerializableIcon>text-x-generic</SerializableIcon>
    <Syntax>asp</Syntax>
  </TextSyntaxItem>
  <TextSyntaxItem>
    <SerializableName>Bash</SerializableName>
    <SerializableDescription>Bash</SerializableDescription>
    <SerializableIcon>text-x-generic</SerializableIcon>
    <Syntax>bash</Syntax>
  </TextSyntaxItem>
  <TextSyntaxItem>
    <SerializableName>C</SerializableName>
    <SerializableDescription>C</SerializableDescription>
    <SerializableIcon>text-x-generic</SerializableIcon>
    <Syntax>c</Syntax>
  </TextSyntaxItem>
  <TextSyntaxItem>
    <SerializableName>Cold Fusion</SerializableName>
    <SerializableDescription>Cold Fusion</SerializableDescription>
    <SerializableIcon>text-x-generic</SerializableIcon>
    <Syntax>cfm</Syntax>
  </TextSyntaxItem>
  <TextSyntaxItem>
    <SerializableName>C++</SerializableName>
    <SerializableDescription>C++</SerializableDescription>
    <SerializableIcon>text-x-generic</SerializableIcon>
    <Syntax>cpp</Syntax>
  </TextSyntaxItem>
  <TextSyntaxItem>
    <SerializableName>C#</SerializableName>
    <SerializableDescription>C#</SerializableDescription>
    <SerializableIcon>text-x-generic</SerializableIcon>
    <Syntax>csharp</Syntax>
  </TextSyntaxItem>
  <TextSyntaxItem>
    <SerializableName>CSS</SerializableName>
    <SerializableDescription>CSS</SerializableDescription>
    <SerializableIcon>text-x-generic</SerializableIcon>
    <Syntax>css</Syntax>
  </TextSyntaxItem>
  <TextSyntaxItem>
    <SerializableName>D</SerializableName>
    <SerializableDescription>D</SerializableDescription>
    <SerializableIcon>text-x-generic</SerializableIcon>
    <Syntax>d</Syntax>
  </TextSyntaxItem>
  <TextSyntaxItem>
    <SerializableName>Delphi</SerializableName>
    <SerializableDescription>Delphi</SerializableDescription>
    <SerializableIcon>text-x-generic</SerializableIcon>
    <Syntax>delphi</Syntax>
  </TextSyntaxItem>
  <TextSyntaxItem>
    <SerializableName>UNIX Diff</SerializableName>
    <SerializableDescription>UNIX Diff</SerializableDescription>
    <SerializableIcon>text-x-generic</SerializableIcon>
    <Syntax>diff</Syntax>
  </TextSyntaxItem>
  <TextSyntaxItem>
    <SerializableName>Eiffel</SerializableName>
    <SerializableDescription>Eiffel</SerializableDescription>
    <SerializableIcon>text-x-generic</SerializableIcon>
    <Syntax>eiffel</Syntax>
  </TextSyntaxItem>
  <TextSyntaxItem>
    <SerializableName>Fortran</SerializableName>
    <SerializableDescription>Fortran</SerializableDescription>
    <SerializableIcon>text-x-generic</SerializableIcon>
    <Syntax>fortran</Syntax>
  </TextSyntaxItem>
  <TextSyntaxItem>
    <SerializableName>HTML 4 Strict</SerializableName>
    <SerializableDescription>HTML 4 Strict</SerializableDescription>
    <SerializableIcon>text-x-generic</SerializableIcon>
    <Syntax>html4strict</Syntax>
  </TextSyntaxItem>
  <TextSyntaxItem>
    <SerializableName>Ini</SerializableName>
    <SerializableDescription>Ini</SerializableDescription>
    <SerializableIcon>text-x-generic</SerializableIcon>
    <Syntax>ini</Syntax>
  </TextSyntaxItem>
  <TextSyntaxItem>
    <SerializableName>Java</SerializableName>
    <SerializableDescription>Java</SerializableDescription>
    <SerializableIcon>text-x-generic</SerializableIcon>
    <Syntax>java</Syntax>
  </TextSyntaxItem>
  <TextSyntaxItem>
    <SerializableName>Java5</SerializableName>
    <SerializableDescription>Java5</SerializableDescription>
    <SerializableIcon>text-x-generic</SerializableIcon>
    <Syntax>java5</Syntax>
  </TextSyntaxItem>
  <TextSyntaxItem>
    <SerializableName>Javascript</SerializableName>
    <SerializableDescription>Javascript</SerializableDescription>
    <SerializableIcon>text-x-generic</SerializableIcon>
    <Syntax>javascript</Syntax>
  </TextSyntaxItem>
  <TextSyntaxItem>
    <SerializableName>LaTeX</SerializableName>
    <SerializableDescription>LaTeX</SerializableDescription>
    <SerializableIcon>text-x-generic</SerializableIcon>
    <Syntax>latex</Syntax>
  </TextSyntaxItem>
  <TextSyntaxItem>
    <SerializableName>LISP</SerializableName>
    <SerializableDescription>LISP</SerializableDescription>
    <SerializableIcon>text-x-generic</SerializableIcon>
    <Syntax>lisp</Syntax>
  </TextSyntaxItem>
  <TextSyntaxItem>
    <SerializableName>Lua</SerializableName>
    <SerializableDescription>Lua</SerializableDescription>
    <SerializableIcon>text-x-generic</SerializableIcon>
    <Syntax>lua</Syntax>
  </TextSyntaxItem>
  <TextSyntaxItem>
    <SerializableName>MATLAB</SerializableName>
    <SerializableDescription>MATLAB</SerializableDescription>
    <SerializableIcon>text-x-generic</SerializableIcon>
    <Syntax>matlab</Syntax>
  </TextSyntaxItem>
  <TextSyntaxItem>
    <SerializableName>Perl</SerializableName>
    <SerializableDescription>Perl</SerializableDescription>
    <SerializableIcon>text-x-generic</SerializableIcon>
    <Syntax>perl</Syntax>
  </TextSyntaxItem>
  <TextSyntaxItem>
    <SerializableName>PHP</SerializableName>
    <SerializableDescription>PHP</SerializableDescription>
    <SerializableIcon>text-x-generic</SerializableIcon>
    <Syntax>php</Syntax>
  </TextSyntaxItem>
  <TextSyntaxItem>
    <SerializableName>Python</SerializableName>
    <SerializableDescription>Python</SerializableDescription>
    <SerializableIcon>text-x-generic</SerializableIcon>
    <Syntax>python</Syntax>
  </TextSyntaxItem>
  <TextSyntaxItem>
    <SerializableName>QBasic / QuickBASIC</SerializableName>
    <SerializableDescription>QBasic / QuickBASIC</SerializableDescription>
    <SerializableIcon>text-x-generic</SerializableIcon>
    <Syntax>qbasic</Syntax>
  </TextSyntaxItem>
  <TextSyntaxItem>
    <SerializableName>Robots</SerializableName>
    <SerializableDescription>Robots</SerializableDescription>
    <SerializableIcon>text-x-generic</SerializableIcon>
    <Syntax>robots</Syntax>
  </TextSyntaxItem>
  <TextSyntaxItem>
    <SerializableName>Ruby</SerializableName>
    <SerializableDescription>Ruby</SerializableDescription>
    <SerializableIcon>text-x-generic</SerializableIcon>
    <Syntax>ruby</Syntax>
  </TextSyntaxItem>
  <TextSyntaxItem>
    <SerializableName>SQL</SerializableName>
    <SerializableDescription>SQL</SerializableDescription>
    <SerializableIcon>text-x-generic</SerializableIcon>
    <Syntax>sql</Syntax>
  </TextSyntaxItem>
  <TextSyntaxItem>
    <SerializableName>TCL</SerializableName>
    <SerializableDescription>TCL</SerializableDescription>
    <SerializableIcon>text-x-generic</SerializableIcon>
    <Syntax>tcl</Syntax>
  </TextSyntaxItem>
  <TextSyntaxItem>
    <SerializableName>Visual BASIC</SerializableName>
    <SerializableDescription>Visual BASIC</SerializableDescription>
    <SerializableIcon>text-x-generic</SerializableIcon>
    <Syntax>vb</Syntax>
  </TextSyntaxItem>
  <TextSyntaxItem>
    <SerializableName>VB.NET</SerializableName>
    <SerializableDescription>VB.NET</SerializableDescription>
    <SerializableIcon>text-x-generic</SerializableIcon>
    <Syntax>vbnet</Syntax>
  </TextSyntaxItem>
  <TextSyntaxItem>
    <SerializableName>Winbatch</SerializableName>
    <SerializableDescription>Winbatch</SerializableDescription>
    <SerializableIcon>text-x-generic</SerializableIcon>
    <Syntax>winbatch</Syntax>
  </TextSyntaxItem>
  <TextSyntaxItem>
    <SerializableName>XML</SerializableName>
    <SerializableDescription>XML</SerializableDescription>
    <SerializableIcon>text-x-generic</SerializableIcon>
    <Syntax>xml</Syntax>
  </TextSyntaxItem>
</ArrayOfTextSyntaxItem>
